expand_fab/__init__.py
expand_fab/expand_fab.py
expand_fab-0.1.1.dist-info/licenses/LICENSE
flutter/expand_fab/pubspec.lock
flutter/expand_fab/pubspec.yaml
flutter/expand_fab/lib/expand_fab.dart
flutter/expand_fab/lib/src/child_fab.dart
flutter/expand_fab/lib/src/expand_fab.dart
flutter/expand_fab/lib/src/extension.dart
expand_fab-0.1.1.dist-info/METADATA
expand_fab-0.1.1.dist-info/WHEEL
expand_fab-0.1.1.dist-info/top_level.txt
expand_fab-0.1.1.dist-info/RECORD
