Metadata-Version: 2.4
Name: expand-fab
Version: 0.1.1
Summary: You can create a floating action button that can be expanded.
Author-email: Arief Minardi <ariefminardi005@gmail.com>
Project-URL: Repository, https://github.com/arief05652/expand-fab
Project-URL: Issues, https://github.com/arief05652/expand-fab/issues
Requires-Python: >=3.12
License-File: LICENSE
Requires-Dist: flet>=0.80.0
Dynamic: license-file
